{
    "section1": {
        "files": [
            {
                "url": "assets/content/tilemap/cobblewood/Cobblewoods.tmj",
                "type": "tilemapTiledJSON",
                "key": "Cobblewoods"
            },
            {
                "url": "assets/content/dino.png",
                "key": "dino",
                "type": "image"
            },
            {
                "url": "assets/content/tilemap/cobblewood/large_earth_tileset.png",
                "frameConfig": {
                    "frameWidth": 32,
                    "frameHeight": 32,
                    "startFrame": 0,
                    "endFrame": -1,
                    "spacing": 0,
                    "margin": 0
                },
                "type": "spritesheet",
                "key": "large_earth_tileset"
            },
            {
                "url": "assets/content/tilemap/cobblewood/medium_earth_tileset.png",
                "frameConfig": {
                    "frameWidth": 32,
                    "frameHeight": 32,
                    "startFrame": 0,
                    "endFrame": -1,
                    "spacing": 0,
                    "margin": 0
                },
                "type": "spritesheet",
                "key": "medium_earth_tileset"
            }
        ]
    },
    "meta": {
        "app": "Phaser Editor 2D - Asset Pack Editor",
        "contentType": "phasereditor2d.pack.core.AssetContentType",
        "url": "https://phasereditor2d.com",
        "version": 2,
        "showAllFilesInBlocks": false
    }
}